odoo10_addon_l10n_br_stock-10.0.1.0.0.99.dev8-nspkg.pth
odoo/addons/l10n_br_stock/README.rst
odoo/addons/l10n_br_stock/__init__.py
odoo/addons/l10n_br_stock/__manifest__.py
odoo/addons/l10n_br_stock/data/l10n_br_stock_data.xml
odoo/addons/l10n_br_stock/i18n/l10n_br_stock.pot
odoo/addons/l10n_br_stock/models/__init__.py
odoo/addons/l10n_br_stock/models/stock.py
odoo/addons/l10n_br_stock/static/description/icon.png
odoo/addons/l10n_br_stock/views/stock_view.xml
odoo10_addon_l10n_br_stock-10.0.1.0.0.99.dev8.dist-info/METADATA
odoo10_addon_l10n_br_stock-10.0.1.0.0.99.dev8.dist-info/WHEEL
odoo10_addon_l10n_br_stock-10.0.1.0.0.99.dev8.dist-info/namespace_packages.txt
odoo10_addon_l10n_br_stock-10.0.1.0.0.99.dev8.dist-info/top_level.txt
odoo10_addon_l10n_br_stock-10.0.1.0.0.99.dev8.dist-info/RECORD
